{
    "loader": "flansmod:turborig",
    "display": {
        "fixed": {
            "translation": [
                6.0,
                6.0,
                6.0
            ],
            "rotation": [
                0.0,
                270.0,
                45.0
            ],
            "scale": [
                1.0,
                1.0,
                1.0
            ]
        },
        "ground": {
            "translation": [
                0.0,
                0.15,
                0.0
            ],
            "rotation": [
                0.0,
                270.0,
                0.0
            ],
            "scale": [
                0.0625,
                0.0625,
                0.0625
            ]
        },
        "head": {
            "translation": [
                0.0,
                0.0,
                0.0
            ],
            "rotation": [
                270.0,
                270.0,
                0.0
            ],
            "scale": [
                1.0,
                1.0,
                1.0
            ]
        },
        "gui": {
            "translation": [
                -0.01894036,
                -0.008928574,
                -0.01894036
            ],
            "rotation": [
                0.0,
                45.0,
                90.0
            ],
            "scale": [
                4.571429,
                4.571429,
                4.571429
            ]
        },
        "thirdperson_lefthand": {
            "translation": [
                8.0,
                8.0,
                6.0
            ],
            "rotation": [
                0.0,
                0.0,
                0.0
            ],
            "scale": [
                1.0,
                1.0,
                1.0
            ]
        },
        "thirdperson_righthand": {
            "translation": [
                8.0,
                8.0,
                6.0
            ],
            "rotation": [
                0.0,
                0.0,
                0.0
            ],
            "scale": [
                1.0,
                1.0,
                1.0
            ]
        },
        "firstperson_lefthand": {
            "translation": [
                -8.0,
                -7.0,
                -13.0
            ],
            "rotation": [
                0.0,
                0.0,
                0.0
            ],
            "scale": [
                1.0,
                1.0,
                1.0
            ]
        },
        "firstperson_righthand": {
            "translation": [
                8.0,
                -7.0,
                -13.0
            ],
            "rotation": [
                0.0,
                0.0,
                0.0
            ],
            "scale": [
                1.0,
                1.0,
                1.0
            ]
        }
    },
    "textures": {
        "default": "flansvendersgame:skins/phantek_4x_optic"
    },
    "icons": {
        "default": "flansvendersgame:item/phantek_4x_optic"
    },
    "animations": {},
    "parts": {
        "body": {
            "origin": [
                0.0,
                0.0,
                0.0
            ],
            "material": "Cutout",
            "turboelements": [
                {
                    "eulerRotations": [
                        0.0,
                        90.0,
                        0.0
                    ],
                    "rotationOrigin": [
                        -0.5000003,
                        0.0,
                        -1.50000024
                    ],
                    "box": {
                        "origin": [
                            0.0,
                            0.0,
                            0.0
                        ],
                        "dimensions": [
                            0.75,
                            1.0,
                            1.0
                        ],
                        "uv": [
                            0,
                            0
                        ]
                    }
                },
                {
                    "eulerRotations": [
                        0.0,
                        90.0,
                        0.0
                    ],
                    "rotationOrigin": [
                        -0.499999821,
                        0.0,
                        1.50000024
                    ],
                    "box": {
                        "origin": [
                            0.0,
                            0.0,
                            0.0
                        ],
                        "dimensions": [
                            0.75,
                            1.25,
                            1.0
                        ],
                        "uv": [
                            4,
                            0
                        ]
                    }
                },
                {
                    "eulerRotations": [
                        0.0,
                        90.0,
                        0.0
                    ],
                    "rotationOrigin": [
                        -0.7499999,
                        1.25,
                        2.0
                    ],
                    "box": {
                        "origin": [
                            0.0,
                            0.0,
                            0.0
                        ],
                        "dimensions": [
                            3.0,
                            1.5,
                            1.5
                        ],
                        "uv": [
                            8,
                            0
                        ]
                    }
                },
                {
                    "eulerRotations": [
                        0.0,
                        90.0,
                        0.0
                    ],
                    "rotationOrigin": [
                        -1.0,
                        1.0,
                        -1.0
                    ],
                    "box": {
                        "origin": [
                            0.0,
                            0.0,
                            0.0
                        ],
                        "dimensions": [
                            3.0,
                            2.0,
                            2.0
                        ],
                        "uv": [
                            18,
                            0
                        ]
                    }
                },
                {
                    "eulerRotations": [
                        0.0,
                        90.0,
                        0.0
                    ],
                    "rotationOrigin": [
                        -1.0,
                        1.0,
                        3.0
                    ],
                    "box": {
                        "origin": [
                            0.0,
                            0.0,
                            0.0
                        ],
                        "dimensions": [
                            1.0,
                            2.0,
                            2.0
                        ],
                        "uv": [
                            0,
                            3
                        ]
                    }
                }
            ]
        }
    },
    "attachPoints": [
        {
            "name": "eye_line",
            "attachTo": "body",
            "offset": [
                -2.38418579E-07,
                2.0,
                3.99999976
            ],
            "euler": [
                0.0,
                0.0,
                0.0
            ]
        }
    ],
    "textureSize": [
        32,
        8
    ]
}